apogee/__init__.py
apogee/core/__init__.py
apogee/core/arrays.py
apogee/core/entropy.py
apogee/core/scaling.py
apogee/core/search.py
apogee/factors/__init__.py
apogee/factors/base.py
apogee/factors/set.py
apogee/factors/discrete/__init__.py
apogee/factors/discrete/estimator.py
apogee/factors/discrete/factor.py
apogee/factors/discrete/operations/__init__.py
apogee/factors/discrete/operations/arithmetic.py
apogee/factors/discrete/operations/divide.py
apogee/factors/discrete/operations/marginalise.py
apogee/factors/discrete/operations/maximise.py
apogee/factors/discrete/operations/product.py
apogee/factors/discrete/operations/random.py
apogee/factors/discrete/operations/reduce.py
apogee/factors/discrete/operations/subtract.py
apogee/factors/discrete/operations/sum.py
apogee/factors/discrete/operations/utils.py
apogee/factors/discrete/operations/fast/__init__.py
apogee/factors/discrete/optimise/__init__.py
apogee/factors/discrete/optimise/basic.py
apogee/inference/__init__.py
apogee/inference/junction_tree.py
apogee/io/__init__.py
apogee/io/parsers/__init__.py
apogee/io/parsers/hugin.py
apogee/models/__init__.py
apogee/models/errors.py
apogee/models/discrete/__init__.py
apogee/models/discrete/network.py
apogee/models/discrete/variable.py
apogee/utils/__init__.py
apogee/utils/draw.py
apogee/utils/loggers.py
apogee/utils/pprint.py
apogee-0.1.2.dist-info/LICENSE
apogee-0.1.2.dist-info/METADATA
apogee-0.1.2.dist-info/WHEEL
apogee-0.1.2.dist-info/top_level.txt
apogee-0.1.2.dist-info/RECORD
