Metadata-Version: 2.1
Name: apogee
Version: 0.1.2
Summary: Apogee
Home-page: UNKNOWN
Author: Mark Douthwaite
Author-email: mark.douthwaite@peak.ai
License: UNKNOWN
Platform: UNKNOWN
Requires-Dist: numpy
Requires-Dist: tornado
Requires-Dist: jupyter
Requires-Dist: networkx
Requires-Dist: matplotlib
Requires-Dist: scipy
